ollm/__init__.py
ollm/attention.py
ollm/gds_loader.py
ollm/gemma3.py
ollm/gpt_oss.py
ollm/gpt_oss_attention.py
ollm/inference.py
ollm/kvcache.py
ollm/llama.py
ollm/qwen3_next.py
ollm/utils.py
ollm/voxtral.py
ollm-1.0.1.dist-info/licenses/LICENSE
ollm-1.0.1.dist-info/METADATA
ollm-1.0.1.dist-info/WHEEL
ollm-1.0.1.dist-info/top_level.txt
ollm-1.0.1.dist-info/RECORD
