Metadata-Version: 2.4
Name: ollm
Version: 1.0.1
Summary: LLM Inference for Large-Context Offline Workloads
Author-email: Anuar Sharafudinov <anuarsh@ailabs.us>
License: MIT License
Project-URL: Homepage, https://github.com/Mega4alik/ollm
Project-URL: Bug Tracker, https://github.com/Mega4alik/ollm/issues
Requires-Python: >=3.10
License-File: LICENSE
Requires-Dist: numpy
Requires-Dist: torch>2.6.0
Requires-Dist: transformers>=4.57.0
Requires-Dist: accelerate
Requires-Dist: flash-linear-attention
Requires-Dist: flash-attn
Dynamic: license-file
